softext/__init__.py
softext/text.py
softext-0.1.1.dist-info/WHEEL
softext-0.1.1.dist-info/METADATA
softext-0.1.1.dist-info/RECORD
